doky/__init__.py
doky/__main__.py
doky/auth_session.py
doky/cli/__init__.py
doky/cli/auth.py
doky/cli/config.py
doky/errors.py
doky/metadatas.py
pyproject.toml
doky-1.0.1.dist-info/LICENSE
doky-1.0.1.dist-info/METADATA
doky-1.0.1.dist-info/WHEEL
doky-1.0.1.dist-info/entry_points.txt
doky-1.0.1.dist-info/RECORD
