Metadata-Version: 2.1
Name: doky
Version: 1.0.1
Summary: Doky is a intuitive library and CLI tool for manage your Docker-In-Docker instances from Play With Docker Lab
Home-page: https://github.com/d3cryptofc/Doky
License: MIT
Author: Lelzin λ
Author-email: d3cryptofc@gmail.com
Requires-Python: >=3.11,<4.0
Classifier: License :: OSI Approved :: MIT License
Classifier: Programming Language :: Python :: 3
Classifier: Programming Language :: Python :: 3.11
Classifier: Programming Language :: Python :: 3.12
Requires-Dist: appdirs (>=1.4.4,<2.0.0)
Requires-Dist: click (>=8.1.7,<9.0.0)
Requires-Dist: httpx[http2] (>=0.26.0,<0.27.0)
Requires-Dist: pyyaml (>=6.0.1,<7.0.0)
Requires-Dist: rich (>=13.7.0,<14.0.0)
Project-URL: Repository, https://github.com/d3cryptofc/Doky
